memorier/main.py
memorier-0.1.0.dist-info/METADATA
memorier-0.1.0.dist-info/WHEEL
memorier-0.1.0.dist-info/top_level.txt
memorier-0.1.0.dist-info/RECORD
