Metadata-Version: 2.4
Name: memorier
Version: 0.1.0
Summary: Add your description here
Requires-Python: >=3.13
